texsite/application/urls.py
texsite/application/wsgi.py
texsite/businesscasual/__init__.py
texsite/businesscasual/apps.py
texsite/businesscasual/blocks.py
texsite/businesscasual/models.py
texsite/businesscasual/migrations/0001_initial.py
texsite/businesscasual/migrations/0002_add_documents_block.py
texsite/businesscasual/migrations/0003_add_people_block.py
texsite/businesscasual/migrations/0004_add_contact_block.py
texsite/businesscasual/migrations/0005_alter_businesscasualpage_body.py
texsite/businesscasual/migrations/__init__.py
texsite/businesscasual/static/css/business-casual.min.css
texsite/businesscasual/static/img/bg.jpg
texsite/businesscasual/templates/texsitebusinesscasual/base.html
texsite/businesscasual/templates/texsitebusinesscasual/business_casual_page.html
texsite/businesscasual/templates/texsitebusinesscasual/login_password.html
texsite/businesscasual/templates/texsitebusinesscasual/blocks/contact.html
texsite/businesscasual/templates/texsitebusinesscasual/blocks/content.html
texsite/businesscasual/templates/texsitebusinesscasual/blocks/documentlist.html
texsite/businesscasual/templates/texsitebusinesscasual/blocks/documents.html
texsite/businesscasual/templates/texsitebusinesscasual/blocks/people.html
texsite/businesscasual/templates/texsitebusinesscasual/blocks/peoplelist.html
texsite/businesscasual/templates/texsitebusinesscasual/menus/footer_menu.html
texsite/businesscasual/templates/texsitebusinesscasual/menus/main_menu.html
texsite/cleanblog/__init__.py
texsite/cleanblog/apps.py
texsite/cleanblog/models.py
texsite/cleanblog/locale/de/LC_MESSAGES/django.mo
texsite/cleanblog/locale/de/LC_MESSAGES/django.po
texsite/cleanblog/locale/en/LC_MESSAGES/django.mo
texsite/cleanblog/locale/en/LC_MESSAGES/django.po
texsite/cleanblog/migrations/0001_initial.py
texsite/cleanblog/migrations/0002_add_quote_block.py
texsite/cleanblog/migrations/0003_change_image_to_image_block.py
texsite/cleanblog/migrations/0004_cleanblogarticleindexpage.py
texsite-5.0.0.dist-info/METADATA
texsite-5.0.0.dist-info/WHEEL
texsite-5.0.0.dist-info/licenses/LICENSE
texsite-5.0.0.dist-info/RECORD
