Metadata-Version: 2.4
Name: texsite
Version: 5.0.0
Project-URL: Homepage, https://www.texperience.de
Project-URL: Repository, https://gitlab.com/texperience/texsite
Author-email: Timo Rieber <trieber@texperience.de>
License: Copyright (c) 2016, Timo Rieber <trieber@texperience.de>
License-File: LICENSE
Classifier: Development Status :: 5 - Production/Stable
Classifier: Environment :: Web Environment
Classifier: Framework :: Django
Classifier: Framework :: Django :: 4.2
Classifier: Framework :: Wagtail
Classifier: Framework :: Wagtail :: 6
Classifier: Intended Audience :: Developers
Classifier: Intended Audience :: End Users/Desktop
Classifier: License :: OSI Approved :: ISC License (ISCL)
Classifier: Operating System :: OS Independent
Classifier: Programming Language :: Python
Classifier: Programming Language :: Python :: 3
Classifier: Programming Language :: Python :: 3.9
Classifier: Programming Language :: Python :: 3.10
Classifier: Programming Language :: Python :: 3.11
Classifier: Programming Language :: Python :: 3.12
Classifier: Programming Language :: Python :: 3.13
Classifier: Topic :: Internet :: WWW/HTTP
Classifier: Topic :: Internet :: WWW/HTTP :: Dynamic Content
Requires-Python: <3.14,>=3.9
Requires-Dist: django-bootstrap-ui<5.0,>=4.0
Requires-Dist: django<4.3,>=4.2
Requires-Dist: wagtail<6.4,>=6.3
Provides-Extra: development
Requires-Dist: coverage<8.0,>=7.8; extra == 'development'
Requires-Dist: ruff<1.0,>=0.11; extra == 'development'
Requires-Dist: tox<5.0,>=4.25; extra == 'development'
Provides-Extra: linting
Requires-Dist: ruff<1.0,>=0.11; extra == 'linting'
Provides-Extra: testing
Requires-Dist: coverage<8.0,>=7.8; extra == 'testing'
Requires-Dist: tox<5.0,>=4.25; extra == 'testing'
